[{"title":"Apollo","description":"budin de naranja","price":"1000","thumbnail":"image","code":"230","stock":"5","id":1},
{"title":"Gea","description":"budin coco","price":"1000","thumbnail":"image","code":"240","stock":"5","id":2},
{"title":"Zeus","description":"budin frutos rojos y vainilla","price":"1000","thumbnail":"image","code":"250","stock":"5","id":3},
{"title":"Venus","description":"budin cacao y banana","price":"1000","thumbnail":"image","code":"260","stock":"5","id":5},
{"title":"Atenea","description":"budin de manzana y canela","price":"1000","thumbnail":"image","code":"270","stock":"5","id":6},
{"title":"Hercules","description":"budin de cacao","price":"1000","thumbnail":"image","code":"280","stock":"5","id":7},
{"title":"Artemisa","description":"budin de peras","price":"1000","thumbnail":"image","code":"290","stock":"5","id":8},
{"title":"Poseidon","description":"budin de limon","price":"1000","thumbnail":"image","code":"300","stock":"5","id":9}]